app/__init__.py
app/main.py
app/mcp_server.py
iflow_mcp_wstcpyt_manim_mcp-0.1.2.dist-info/licenses/LICENSE
iflow_mcp_wstcpyt_manim_mcp-0.1.2.dist-info/METADATA
iflow_mcp_wstcpyt_manim_mcp-0.1.2.dist-info/WHEEL
iflow_mcp_wstcpyt_manim_mcp-0.1.2.dist-info/entry_points.txt
iflow_mcp_wstcpyt_manim_mcp-0.1.2.dist-info/top_level.txt
iflow_mcp_wstcpyt_manim_mcp-0.1.2.dist-info/RECORD
