Metadata-Version: 2.4
Name: iflow-mcp-wstcpyt-manim-mcp
Version: 0.1.2
Summary: A Docker-based environment for creating mathematical animations with Manim, featuring MCP support
Author-email: wstcpyt <noreply@example.com>
License: Apache-2.0
Keywords: manim,mcp,fastapi,animation,math
Classifier: Development Status :: 4 - Beta
Classifier: Intended Audience :: Developers
Classifier: License :: OSI Approved :: Apache Software License
Classifier: Programming Language :: Python :: 3
Classifier: Programming Language :: Python :: 3.11
Classifier: Programming Language :: Python :: 3.12
Classifier: Topic :: Scientific/Engineering :: Visualization
Requires-Python: >=3.11
License-File: LICENSE
Requires-Dist: fastapi>=0.104.0
Requires-Dist: uvicorn>=0.24.0
Requires-Dist: pydantic>=2.0.0
Requires-Dist: python-multipart>=0.0.6
Requires-Dist: fastapi-mcp>=0.3.0
Provides-Extra: dev
Requires-Dist: pytest>=7.0.0; extra == "dev"
Requires-Dist: httpx>=0.25.0; extra == "dev"
Dynamic: license-file
